gooee/__init__.py
gooee/client.py
gooee/compat.py
gooee/decorators.py
gooee/exceptions.py
gooee/models.py
gooee/utils.py
gooee_sdk-0.1.2.dist-info/DESCRIPTION.rst
gooee_sdk-0.1.2.dist-info/METADATA
gooee_sdk-0.1.2.dist-info/RECORD
gooee_sdk-0.1.2.dist-info/WHEEL
gooee_sdk-0.1.2.dist-info/metadata.json
gooee_sdk-0.1.2.dist-info/top_level.txt
